aun_detection/__init__.py
aun_detection/operator.py
aun_detection-0.1.3.dist-info/licenses/LICENSE
aun_detection-0.1.3.dist-info/METADATA
aun_detection-0.1.3.dist-info/WHEEL
aun_detection-0.1.3.dist-info/top_level.txt
aun_detection-0.1.3.dist-info/RECORD
